binance_us/__init__.py
binance_us/binance_us.py
binance_us-0.0.14.dist-info/LICENSE
binance_us-0.0.14.dist-info/METADATA
binance_us-0.0.14.dist-info/WHEEL
binance_us-0.0.14.dist-info/top_level.txt
binance_us-0.0.14.dist-info/RECORD
