Metadata-Version: 2.2
Name: binance-us
Version: 0.0.14
Summary: A simple package for connecting to the the Binance US API.
Author-email: Nikhil Sunder <nsunder724@gmail.com>
Maintainer-email: Nikhil Sunder <nsunder724@gmail.com>
License:                     GNU AFFERO GENERAL PUBLIC LICENSE
Project-URL: Repository, https://github.com/nikhilxsunder/binance-us
Project-URL: Issues, https://github.com/nikhilxsunder/binance-us/issues
Project-URL: Documentation, https://docs.binance.us/#introduction
Keywords: binance,crypto,api,finance,binance api
Classifier: Programming Language :: Python :: 3
Classifier: License :: OSI Approved :: GNU Affero General Public License v3
Classifier: Operating System :: OS Independent
Classifier: Development Status :: 4 - Beta
Classifier: Intended Audience :: Financial and Insurance Industry
Classifier: Topic :: Office/Business :: Financial :: Investment
Requires-Python: >=3.8
License-File: LICENSE
Requires-Dist: requests
